promptgenio/__init__.py
promptgenio/promptgenio.py
promptgenio-0.3.dist-info/METADATA
promptgenio-0.3.dist-info/WHEEL
promptgenio-0.3.dist-info/top_level.txt
promptgenio-0.3.dist-info/RECORD
