Metadata-Version: 2.1
Name: promptgenio
Version: 0.3
Summary: A Python package for PromptGenio integration
Home-page: https://github.com/christiannmadsen/promptgenio-python
Author: Christian Madsen
Author-email: hej@echristiannmadsen.dk
Classifier: Programming Language :: Python :: 3
Classifier: License :: OSI Approved :: MIT License
Classifier: Operating System :: OS Independent
Requires-Python: >=3.6
Requires-Dist: requests
Requires-Dist: groq
